scripts/__init__.py
scripts/annotate.py
scripts/convert_1_0_to_1_2.py
scripts/convert_2_0_to_1_2.py
scripts/convert_articles_and_reflexives.py
scripts/count_parents_children.py
scripts/count_tokens.py
scripts/evaluate_db.py
scripts/evaluate_standard.py
scripts/find_constructions.py
scripts/fix_tokenization.py
scripts/join_passages.py
scripts/join_sdp.py
scripts/load_word_vectors.py
scripts/match_text.py
scripts/normalize.py
scripts/pickle_to_standard.py
scripts/remove_br_tokens.py
scripts/replace_tokens_by_dict.py
scripts/set_external_id_offline.py
scripts/site_pickle_to_standard.py
scripts/site_to_standard.py
scripts/site_to_text.py
scripts/split_corpus.py
scripts/standard_to_json.py
scripts/standard_to_paragraphs.py
scripts/standard_to_pickle.py
scripts/standard_to_sentences.py
scripts/standard_to_site.py
scripts/standard_to_text.py
scripts/statistics.py
scripts/text_to_standard.py
scripts/unique_roles.py
scripts/validate.py
scripts/visualize.py
scripts/visualize_as_text.py
scripts/distances/__init__.py
scripts/distances/align.py
ucca/__init__.py
ucca/__version__.py
ucca/constructions.py
ucca/convert.py
ucca/core.py
ucca/diffutil.py
ucca/evaluation.py
ucca/ioutil.py
ucca/layer0.py
ucca/layer1.py
ucca/normalization.py
ucca/textutil.py
ucca/validation.py
ucca/visualization.py
ucca/tests/__init__.py
ucca/tests/conftest.py
ucca/tests/test_constructions.py
ucca/tests/test_convert.py
ucca/tests/test_core.py
ucca/tests/test_evaluation.py
ucca/tests/test_ioutil.py
ucca/tests/test_layer0.py
ucca/tests/test_layer1.py
ucca/tests/test_normalization.py
ucca/tests/test_textutil.py
ucca/tests/test_validation.py
ucca/tests/test_visualization.py
ucca_db/__init__.py
ucca_db/api.py
ucca_db/download.py
ucca_db/upload.py
uccaapp/__init__.py
uccaapp/api.py
uccaapp/convert_and_evaluate.py
uccaapp/copy_categories.py
uccaapp/create_annotation_tasks.py
uccaapp/create_tokenization_tasks.py
uccaapp/download_task.py
uccaapp/evaluate.py
uccaapp/export_units_by_filter.py
UCCA-1.3.11.dist-info/LICENSE.txt
UCCA-1.3.11.dist-info/METADATA
UCCA-1.3.11.dist-info/WHEEL
UCCA-1.3.11.dist-info/top_level.txt
UCCA-1.3.11.dist-info/RECORD
