Metadata-Version: 2.1
Name: UCCA
Version: 1.3.11
Summary: Universal Conceptual Cognitive Annotation
Home-page: https://github.com/huji-nlp/ucca
Author: Daniel Hershcovich
Author-email: danielh@cs.huji.ac.il
License: UNKNOWN
Platform: UNKNOWN
Classifier: Development Status :: 4 - Beta
Classifier: Intended Audience :: Science/Research
Classifier: Programming Language :: Python :: 3.6
Classifier: Topic :: Text Processing :: Linguistic
Classifier: License :: OSI Approved :: GNU General Public License v3 or later (GPLv3+)
Provides-Extra: distances
Provides-Extra: visualize
